autophyslearn/__init__.py
autophyslearn/postprocessing/__init__.py
autophyslearn/postprocessing/complex.py
autophyslearn/preprocessing/__init__.py
autophyslearn/spectroscopic/__init__.py
autophyslearn/spectroscopic/nn.py
AutoPhysLearn-0.2.5.dist-info/LICENSE.txt
AutoPhysLearn-0.2.5.dist-info/METADATA
AutoPhysLearn-0.2.5.dist-info/WHEEL
AutoPhysLearn-0.2.5.dist-info/top_level.txt
AutoPhysLearn-0.2.5.dist-info/RECORD
