Metadata-Version: 2.1
Name: AutoPhysLearn
Version: 0.2.5
Summary: A python package for physics constrained machine learning by the M3-learning research group at Drexel University
Home-page: https://github.com/pyscaffold/pyscaffold/
Author: jagar2
Author-email: jca92@drexel.edu
License: MIT
Project-URL: Documentation, https://pyscaffold.org/
Platform: Linux
Classifier: Development Status :: 4 - Beta
Classifier: Programming Language :: Python
Requires-Python: >=3.9
License-File: LICENSE.txt
Requires-Dist: torch
Requires-Dist: numpy
Requires-Dist: m3learning-util
Requires-Dist: importlib-metadata ; python_version > "3.9"
Provides-Extra: testing
Requires-Dist: setuptools ; extra == 'testing'
Requires-Dist: pytest ; extra == 'testing'
Requires-Dist: pytest-cov ; extra == 'testing'
